contextagent/__init__.py
contextagent/agent/__init__.py
contextagent/agent/agent.py
contextagent/agent/executor.py
contextagent/agent/tracker.py
contextagent/artifacts/__init__.py
contextagent/artifacts/artifact_writer.py
contextagent/artifacts/reporter.py
contextagent/artifacts/terminal_writer.py
contextagent/context/__init__.py
contextagent/context/context.py
contextagent/context/conversation.py
contextagent/context/data_store.py
contextagent/llm/llm_setup.py
contextagent/mcp/manager.py
contextagent/mcp/patches.py
contextagent/mcp/servers/chrome_devtools/server.py
contextagent/profiles/base.py
contextagent/profiles/data/data_analysis.py
contextagent/profiles/data/data_loader.py
contextagent/profiles/data/evaluation.py
contextagent/profiles/data/model_training.py
contextagent/profiles/data/preprocessing.py
contextagent/profiles/data/visualization.py
contextagent/profiles/debug/vanilla_chat.py
contextagent/profiles/manager/evaluate.py
contextagent/profiles/manager/memory.py
contextagent/profiles/manager/observe.py
contextagent/profiles/manager/routing.py
contextagent/profiles/manager/writer.py
contextagent/profiles/mcp/browser.py
contextagent/profiles/mcp/chrome.py
contextagent/profiles/mcp/notion.py
contextagent/profiles/web/web_crawler.py
contextagent/profiles/web/web_planning.py
contextagent/profiles/web/web_searcher.py
contextagent/tools/__init__.py
contextagent/tools/data_tools/__init__.py
contextagent/tools/data_tools/data_analysis.py
contextagent/tools/data_tools/data_loading.py
contextagent/tools/data_tools/evaluation.py
contextagent/tools/data_tools/helpers.py
contextagent/tools/data_tools/image.py
contextagent/tools/data_tools/model_training.py
contextagent/tools/data_tools/preprocessing.py
contextagent/tools/data_tools/video.py
contextagent/tools/data_tools/visualization.py
contextagent/tools/web_tools/__init__.py
contextagent/tools/web_tools/crawl.py
contextagent/tools/web_tools/old_search.py
contextagent/tools/web_tools/search.py
contextagent-0.1.1.dist-info/licenses/LICENSE
contextagent-0.1.1.dist-info/METADATA
contextagent-0.1.1.dist-info/WHEEL
contextagent-0.1.1.dist-info/top_level.txt
contextagent-0.1.1.dist-info/RECORD
