Metadata-Version: 2.4
Name: contextagent
Version: 0.1.1
Summary: A Context-Central Multi-Agent System Platform
Author-email: Zhimeng Guo <gzjz07@outlook.com>
License: MIT
Project-URL: Homepage, https://github.com/TimeLovercc/contextagent
Project-URL: Repository, https://github.com/TimeLovercc/contextagent
Project-URL: Documentation, https://github.com/TimeLovercc/contextagent#readme
Project-URL: Bug Tracker, https://github.com/TimeLovercc/contextagent/issues
Keywords: agent,multi-agent,ai,llm,research,machine-learning,autonomous-agents
Classifier: Development Status :: 3 - Alpha
Classifier: Intended Audience :: Developers
Classifier: Intended Audience :: Science/Research
Classifier: License :: OSI Approved :: MIT License
Classifier: Programming Language :: Python :: 3
Classifier: Programming Language :: Python :: 3.11
Classifier: Topic :: Scientific/Engineering :: Artificial Intelligence
Requires-Python: >=3.11
License-File: LICENSE
Requires-Dist: aiohttp>=3.9.0
Requires-Dist: beautifulsoup4>=4.12.0
Requires-Dist: build>=1.3.0
Requires-Dist: flask>=3.1.2
Requires-Dist: google-generativeai>=0.8.5
Requires-Dist: ipdb>=0.13.13
Requires-Dist: litellm==1.76
Requires-Dist: loguru>=0.7.3
Requires-Dist: lxml>=6.0.2
Requires-Dist: markdown>=3.5.0
Requires-Dist: matplotlib>=3.10.6
Requires-Dist: numpy>=2.3.3
Requires-Dist: openai-agents>=0.3.2
Requires-Dist: pandas>=2.3.3
Requires-Dist: pygments>=2.17.0
Requires-Dist: requests>=2.32.5
Requires-Dist: rich>=14.1.0
Requires-Dist: scikit-learn>=1.7.2
Requires-Dist: seaborn>=0.13.2
Requires-Dist: twine>=6.2.0
Requires-Dist: weave>=0.52.8
Dynamic: license-file
